{"cameraMode":{"drawMode":0,"name":"Shaded","section":"Shading Mode"},"sceneLighting":false,"audioPlay":false,"sceneViewState":{"m_AlwaysRefresh":false,"showFog":true,"showSkybox":false,"showFlares":true,"showImageEffects":true,"showParticleSystems":true,"showVisualEffectGraphs":true,"m_FxEnabled":true},"in2DMode":false,"pivot":{"x":0.027218172326683999,"y":-0.027685251086950303,"z":-0.032584793865680698},"rotation":{"x":-0.007059668656438589,"y":0.7401774525642395,"z":0.007771956268697977,"w":0.6723241209983826},"size":0.10347092151641846,"orthographic":false}